SpringAmqp212ReleaseZhongwenWendang/README.md
SpringAmqp212ReleaseZhongwenWendang/__init__.py
SpringAmqp212ReleaseZhongwenWendang/__main__.py
SpringAmqp212ReleaseZhongwenWendang/file.epub
SpringAmqp212ReleaseZhongwenWendang/index.html
SpringAmqp212ReleaseZhongwenWendang/css/__init__.py
SpringAmqp212ReleaseZhongwenWendang/css/annotations.css
SpringAmqp212ReleaseZhongwenWendang/css/main.css
SpringAmqp212ReleaseZhongwenWendang/css/normalize.css
SpringAmqp212ReleaseZhongwenWendang/css/popup.css
SpringAmqp212ReleaseZhongwenWendang/font/__init__.py
SpringAmqp212ReleaseZhongwenWendang/font/fontello.eot
SpringAmqp212ReleaseZhongwenWendang/font/fontello.svg
SpringAmqp212ReleaseZhongwenWendang/font/fontello.ttf
SpringAmqp212ReleaseZhongwenWendang/font/fontello.woff
SpringAmqp212ReleaseZhongwenWendang/img/__init__.py
SpringAmqp212ReleaseZhongwenWendang/img/annotator-glyph-sprite.png
SpringAmqp212ReleaseZhongwenWendang/img/annotator-icon-sprite.png
SpringAmqp212ReleaseZhongwenWendang/img/apple-touch-icon.png
SpringAmqp212ReleaseZhongwenWendang/img/cancelfullscreen.png
SpringAmqp212ReleaseZhongwenWendang/img/close.png
SpringAmqp212ReleaseZhongwenWendang/img/fullscreen.png
SpringAmqp212ReleaseZhongwenWendang/img/loader.gif
SpringAmqp212ReleaseZhongwenWendang/img/menu-icon.png
SpringAmqp212ReleaseZhongwenWendang/img/save.png
SpringAmqp212ReleaseZhongwenWendang/img/saved.png
SpringAmqp212ReleaseZhongwenWendang/img/settings-s.png
SpringAmqp212ReleaseZhongwenWendang/img/settings.png
SpringAmqp212ReleaseZhongwenWendang/img/star.png
SpringAmqp212ReleaseZhongwenWendang/js/__init__.py
SpringAmqp212ReleaseZhongwenWendang/js/epub.js
SpringAmqp212ReleaseZhongwenWendang/js/epub.min.js
SpringAmqp212ReleaseZhongwenWendang/js/epub.min.map
SpringAmqp212ReleaseZhongwenWendang/js/hooks.min.js
SpringAmqp212ReleaseZhongwenWendang/js/hooks.min.map
SpringAmqp212ReleaseZhongwenWendang/js/reader.js
SpringAmqp212ReleaseZhongwenWendang/js/reader.js.map
SpringAmqp212ReleaseZhongwenWendang/js/reader.min.js
spring_amqp_2_1_2_release_zhongwen_wendang-2024.3.5.0.dist-info/METADATA
spring_amqp_2_1_2_release_zhongwen_wendang-2024.3.5.0.dist-info/WHEEL
spring_amqp_2_1_2_release_zhongwen_wendang-2024.3.5.0.dist-info/entry_points.txt
spring_amqp_2_1_2_release_zhongwen_wendang-2024.3.5.0.dist-info/top_level.txt
spring_amqp_2_1_2_release_zhongwen_wendang-2024.3.5.0.dist-info/RECORD
